{
  "claim": {
    "id": "acg_claim_K2_001",
    "timestamp": "2026-01-31T10:20:00Z",
    "target": "oracle_town/jobs/obs_scan.py",
    "claim_type": "code_change",
    "proposed_diffs": [
      {
        "path": "obs_scan.py",
        "operation": "modify",
        "hash_before": "a",
        "hash_after": "b"
      }
    ],
    "evidence_pointers": [
      {
        "type": "test_result",
        "path": "acg_claim_K2_001_evidence_0.txt",
        "hash": "sha256:08f8bbea8610876164db6ff0fcca66c4b69840a1301392c838d57cf8adee9427",
        "description": "Generated by claim"
      }
    ],
    "acceptance_criteria": [
      "test_pass"
    ],
    "policy_pack_hash": "sha256:policy_v1_2026_01",
    "generated_by": "test-legal-001",
    "intent": "Test self-generated evidence rejection",
    "expected_outcomes": [],
    "acg": {
      "intended_primary_gate": "K2_no_self_attestation",
      "category": "K2",
      "variant": "test"
    }
  }
}